nextline_rdb/.gitignore
nextline_rdb/__about__.py
nextline_rdb/__init__.py
nextline_rdb/db.py
nextline_rdb/default.toml
nextline_rdb/init.py
nextline_rdb/pagination.py
nextline_rdb/plugin.py
nextline_rdb/py.typed
nextline_rdb/alembic/README.md
nextline_rdb/alembic/alembic.ini
nextline_rdb/alembic/conftest.py
nextline_rdb/alembic/env.py
nextline_rdb/alembic/script.py.mako
nextline_rdb/alembic/models/__init__.py
nextline_rdb/alembic/models/conftest.py
nextline_rdb/alembic/models/rev_245c4152e8d7/__init__.py
nextline_rdb/alembic/models/rev_245c4152e8d7/conftest.py
nextline_rdb/alembic/models/rev_245c4152e8d7/model_hello.py
nextline_rdb/alembic/models/rev_245c4152e8d7/model_prompt.py
nextline_rdb/alembic/models/rev_245c4152e8d7/model_run.py
nextline_rdb/alembic/models/rev_245c4152e8d7/model_script.py
nextline_rdb/alembic/models/rev_245c4152e8d7/model_stdout.py
nextline_rdb/alembic/models/rev_245c4152e8d7/model_trace.py
nextline_rdb/alembic/models/rev_245c4152e8d7/base/__init__.py
nextline_rdb/alembic/models/rev_245c4152e8d7/base/convention.py
nextline_rdb/alembic/models/rev_245c4152e8d7/base/model_base.py
nextline_rdb/alembic/models/rev_245c4152e8d7/base/repr_.py
nextline_rdb/alembic/models/rev_4dc6a93dfed8/__init__.py
nextline_rdb/alembic/models/rev_4dc6a93dfed8/conftest.py
nextline_rdb/alembic/models/rev_4dc6a93dfed8/model_hello.py
nextline_rdb/alembic/models/rev_4dc6a93dfed8/model_prompt.py
nextline_rdb/alembic/models/rev_4dc6a93dfed8/model_run.py
nextline_rdb/alembic/models/rev_4dc6a93dfed8/model_script.py
nextline_rdb/alembic/models/rev_4dc6a93dfed8/model_stdout.py
nextline_rdb/alembic/models/rev_4dc6a93dfed8/model_trace.py
nextline_rdb/alembic/models/rev_4dc6a93dfed8/base/__init__.py
nextline_rdb/alembic/models/rev_4dc6a93dfed8/base/convention.py
nextline_rdb/alembic/models/rev_4dc6a93dfed8/base/model_base.py
nextline_rdb/alembic/models/rev_4dc6a93dfed8/base/repr_.py
nextline_rdb/alembic/models/rev_4dc6a93dfed8/strategies/__init__.py
nextline_rdb-0.7.0.dist-info/METADATA
nextline_rdb-0.7.0.dist-info/WHEEL
nextline_rdb-0.7.0.dist-info/entry_points.txt
nextline_rdb-0.7.0.dist-info/licenses/LICENSE.txt
nextline_rdb-0.7.0.dist-info/RECORD
