Metadata-Version: 2.4
Name: nextline-rdb
Version: 0.7.0
Summary: A plugin of nextline-graphql. A relational database for nextline
Project-URL: Documentation, https://github.com/simonsobs/nextline-rdb#readme
Project-URL: Issues, https://github.com/simonsobs/nextline-rdb/issues
Project-URL: Source, https://github.com/simonsobs/nextline-rdb
Author-email: Simons Observatory <so_software@simonsobservatory.org>
License-Expression: MIT
License-File: LICENSE.txt
Classifier: Development Status :: 4 - Beta
Classifier: Intended Audience :: Science/Research
Classifier: License :: OSI Approved :: MIT License
Classifier: Programming Language :: Python
Classifier: Programming Language :: Python :: 3.10
Classifier: Programming Language :: Python :: 3.11
Classifier: Programming Language :: Python :: 3.12
Classifier: Programming Language :: Python :: 3.13
Requires-Python: >=3.10
Requires-Dist: aiosqlite>=0.16
Requires-Dist: alembic>=1.9
Requires-Dist: hypothesis>=6.88
Requires-Dist: nextline-graphql>=0.7.9
Requires-Dist: nextline>=0.7.14
Requires-Dist: sqlalchemy[asyncio]>=2.0.31
Requires-Dist: tomli-w>=1.0
Requires-Dist: tomli>=2.0
Provides-Extra: tests
Requires-Dist: async-asgi-testclient>=1.4.10; extra == 'tests'
Requires-Dist: nextline-test-utils>=0.1; extra == 'tests'
Requires-Dist: pytest-asyncio>=0.18; extra == 'tests'
Requires-Dist: pytest-cov>=3.0; extra == 'tests'
Requires-Dist: pytest-timeout>=2.1; extra == 'tests'
Requires-Dist: pytest>=7.0; extra == 'tests'
